gpytranslate/__init__.py
gpytranslate/exceptions.py
gpytranslate/gpytranslate.py
gpytranslate/py.typed
gpytranslate/sync/__init__.py
gpytranslate/sync/sync_translator.py
gpytranslate/types/__init__.py
gpytranslate/types/base_translator.py
gpytranslate/types/translated_object.py
gpytranslate-2.1.0.dist-info/LICENSE
gpytranslate-2.1.0.dist-info/METADATA
gpytranslate-2.1.0.dist-info/WHEEL
gpytranslate-2.1.0.dist-info/RECORD
