Metadata-Version: 2.3
Name: gpytranslate
Version: 2.1.0
Summary: A Python3 library for translating text using Google Translate API.
License: MIT
Author: Davide Galilei
Author-email: davidegalilei2018@gmail.com
Maintainer: Davide Galilei
Maintainer-email: davidegalilei2018@gmail.com
Requires-Python: >=3.12,<4.0
Classifier: License :: OSI Approved :: MIT License
Classifier: Operating System :: OS Independent
Classifier: Programming Language :: Python :: 3
Classifier: Programming Language :: Python :: 3.12
Classifier: Programming Language :: Python :: 3.13
Requires-Dist: aiofiles (>=25.1.0,<26.0)
Requires-Dist: httpx[socks] (>=0.28.1,<2.0)
Requires-Dist: typing-extensions (>=4.15.0,<6.0)
Project-URL: Bug Tracker, https://github.com/DavideGalilei/gpytranslate/issues
Project-URL: Homepage, https://github.com/DavideGalilei/gpytranslate
